backend/__init__.py
backend/utils.py
backend/memory/__init__.py
backend/memory/draft.py
backend/memory/research.py
backend/report_type/__init__.py
backend/report_type/basic_report/__init__.py
backend/report_type/basic_report/basic_report.py
backend/report_type/detailed_report/__init__.py
backend/report_type/detailed_report/detailed_report.py
backend/server/__init__.py
backend/server/server.py
backend/server/server_utils.py
backend/server/websocket_manager.py
gpt_researcher/__init__.py
gpt_researcher/agent.py
gpt_researcher/prompts.py
gpt_researcher/actions/__init__.py
gpt_researcher/actions/agent_creator.py
gpt_researcher/actions/markdown_processing.py
gpt_researcher/actions/query_processing.py
gpt_researcher/actions/report_generation.py
gpt_researcher/actions/retriever.py
gpt_researcher/actions/utils.py
gpt_researcher/actions/web_scraping.py
gpt_researcher/config/__init__.py
gpt_researcher/config/config.py
gpt_researcher/config/variables/__init__.py
gpt_researcher/config/variables/base.py
gpt_researcher/config/variables/default.py
gpt_researcher/context/__init__.py
gpt_researcher/context/compression.py
gpt_researcher/context/retriever.py
gpt_researcher/document/__init__.py
gpt_researcher/document/document.py
gpt_researcher/document/langchain_document.py
gpt_researcher/llm_provider/__init__.py
gpt_researcher/llm_provider/generic/__init__.py
gpt_researcher/llm_provider/generic/base.py
gpt_researcher/memory/__init__.py
gpt_researcher/memory/embeddings.py
gpt_researcher/retrievers/__init__.py
gpt_researcher/retrievers/utils.py
gpt_researcher/retrievers/arxiv/__init__.py
gpt_researcher/retrievers/arxiv/arxiv.py
gpt_researcher/retrievers/bing/__init__.py
gpt_researcher/retrievers/bing/bing.py
gpt_researcher/retrievers/custom/__init__.py
gpt_researcher/retrievers/custom/custom.py
gpt_researcher/retrievers/duckduckgo/__init__.py
gpt_researcher/retrievers/duckduckgo/duckduckgo.py
gpt_researcher/retrievers/exa/__init__.py
gpt_researcher/retrievers/exa/exa.py
gpt_researcher-1.0.1.dist-info/LICENSE
gpt_researcher-1.0.1.dist-info/METADATA
gpt_researcher-1.0.1.dist-info/WHEEL
gpt_researcher-1.0.1.dist-info/top_level.txt
gpt_researcher-1.0.1.dist-info/RECORD
