Metadata-Version: 2.1
Name: gpt-researcher
Version: 1.0.1
Summary: GPT Researcher is an autonomous agent designed for comprehensive web research on any task
Home-page: https://github.com/assafelovic/gpt-researcher
Author: Assaf Elovic
Author-email: assaf.elovic@gmail.com
License: MIT
Classifier: License :: OSI Approved :: MIT License
Classifier: Intended Audience :: Developers
Classifier: Intended Audience :: Education
Classifier: Intended Audience :: Science/Research
Classifier: Programming Language :: Python :: 3.11
Classifier: Programming Language :: Python :: 3.12
Classifier: Topic :: Scientific/Engineering :: Artificial Intelligence
License-File: LICENSE
Requires-Dist: beautifulsoup4
Requires-Dist: colorama
Requires-Dist: md2pdf
Requires-Dist: python-dotenv
Requires-Dist: pyyaml
Requires-Dist: pydantic
Requires-Dist: python-multipart
Requires-Dist: markdown
Requires-Dist: langchain<0.3,>=0.2
Requires-Dist: langchain_community<0.3,>=0.2
Requires-Dist: langchain-openai<0.2,>=0.1
Requires-Dist: tiktoken
Requires-Dist: arxiv
Requires-Dist: PyMuPDF
Requires-Dist: requests
Requires-Dist: aiofiles
Requires-Dist: mistune
Requires-Dist: python-docx
Requires-Dist: htmldocx
Requires-Dist: lxml_html_clean
Requires-Dist: websockets
Requires-Dist: unstructured
Requires-Dist: json_repair
Requires-Dist: json5
Requires-Dist: loguru
